Workbook

Sheet Dashboard & Summary
A1: EXECUTIVE DATA ANALYSIS & KPI DASHBOARD
A3: Last Refreshed Timestamp: | B3: =NOW()
B5: Total Revenue =SUM(Dataset!E2:E201) | E5: Total Profit =SUM(Dataset!I2:I201) | H5: Total Quantity Sold =SUM(Dataset!F2:F201)
A8: Project Tasks Execution Summary
A10: Task # | B10: Task Name | C10: Implementation Status & Details
A11: Task 1 | B11: Top 10 Customers | C11: Highlighted using Conditional Formatting in 'Top Customers' sheet.
A12: Task 2 | B12: What-If Analysis | C12: Modeled scenario table on Discount sensitivity in 'What-If Analysis' sheet.
A13: Task 3 | B13: Linear Regression | C13: Calculated Regression parameters (Profit vs Sales) in 'Regression Analysis' sheet.
A14: Task 4 | B14: Descriptive Statistics | C14: Full metrics summary computed in 'Descriptive Stats' sheet.
A15: Task 5 | B15: Monthly Sales Growth | C15: Calculated MoM growth with ↑ / ↓ indicator arrows in 'Monthly Growth' sheet.
A16: Task 6 | B16: Timestamp | C16: Implemented dynamic `=NOW()` formula on Dashboard.
A17: Task 7 | B17: High-Value Customers | C17: Extracted using INDEX/MATCH and Grouping logic in 'High Value Customers' sheet.
A18: Task 8 | B18: Pivot Table | C18: Sales aggregated by Region and Category in 'Pivot Table' sheet.
A19: Task 9 | B19: Bar, Line & Pie Charts | C19: Embedded visual charts across relevant analytical sheets.
A20: Task 10 | B20: Dashboard & Storytelling | C20: Unified insights consolidated on this dashboard sheet.

Sheet Dataset
A1: Customer_ID | B1: Customer_Name | C1: Region | D1: Product_Category | E1: Sales | F1: Quantity | G1: Discount | H1: Order_Date | I1: Profit
A2: CUST019 | B2: James Davis | C2: West | D2: Books | E2: 1036.09 | F2: 4 | G2: 0.2 | H2: 2024-04-10 | I2: 331.55
A3: CUST012 | B3: Robert Anderson | C3: West | D3: Clothing | E3: 1101.28 | F3: 3 | G3: 0.2 | H3: 2024-04-11 | I3: 440.51
A4: CUST017 | B4: James Taylor | C4: East | D4: Books | E4: 713.34 | F4: 17 | G4: 0 | H4: 2024-04-14 | I4: 285.34
A5: CUST005 | B5: Robert Anderson | C5: South | D5: Electronics | E5: 760.93 | F5: 4 | G5: 0.15 | H5: 2024-04-14 | I5: 161.7
A6: CUST030 | B6: James Wilson | C6: North | D6: Books | E6: 847 | F6: 12 | G6: 0.2 | H6: 2024-04-15 | I6: 271.04
A7: CUST007 | B7: Michael Anderson | C7: North | D7: Furniture | E7: 965.64 | F7: 8 | G7: 0.1 | H7: 2024-04-16 | I7: 304.18
A8: CUST001 | B8: Linda Wilson | C8: West | D8: Electronics | E8: 1317.53 | F8: 12 | G8: 0.05 | H8: 2024-04-16 | I8: 312.91
A9: CUST026 | B9: Mary Davis | C9: East | D9: Furniture | E9: 1074.47 | F9: 6 | G9: 0.2 | H9: 2024-04-19 | I9: 300.85
A10: CUST009 | B10: Linda Jackson | C10: Central | D10: Books | E10: 501.54 | F10: 11 | G10: 0.05 | H10: 2024-04-19 | I10: 190.59
A11: CUST010 | B11: David Thomas | C11: Central | D11: Clothing | E11: 737.31 | F11: 2 | G11: 0.05 | H11: 2024-04-19 | I11: 350.22
A12: CUST014 | B12: Emma Davis | C12: West | D12: Office Supplies | E12: 1572.82 | F12: 6 | G12: 0.05 | H12: 2024-04-20 | I12: 672.38
A13: CUST014 | B13: David Thomas | C13: Central | D13: Books | E13: 1343.13 | F13: 14 | G13: 0.15 | H13: 2024-04-22 | I13: 456.66
... A201: CUST016 | B201: David Thomas | C201: South | D201: Clothing | E201: 928.32 | F201: 2 | G201: 0.05 | H201: 2025-04-07 | I201: 440.95

Sheet Top Customers
A1: Task 1: Top 10 Customers (Conditional Formatting Applied)
A3: Customer ID | B3: Customer Name | C3: Total Purchase (Sales)
A4: CUST015 | B4: James Wilson | C4: 4831.49
A5: CUST028 | B5: James Wilson | C5: 3687.46
A6: CUST003 | B6: James Wilson | C6: 3095.83
A7: CUST026 | B7: Mary Davis | C7: 2653.2
A8: CUST014 | B8: Emma Davis | C8: 2637.01
A9: CUST030 | B9: Mary Davis | C9: 2401.45
A10: CUST003 | B10: James Davis | C10: 2341.4
A11: CUST029 | B11: Emma Wilson | C11: 2273.07
A12: CUST007 | B12: David Brown | C12: 2173.2
A13: CUST004 | B13: Mary Davis | C13: 2162.74
A14: CUST007 | B14: Michael Anderson | C14: 2157.22
A15: CUST008 | B15: James Wilson | C15: 2095.36
... A174: CUST001 | B174: David Anderson | C174: 336.66

Sheet What-If Analysis
A1: Task 2: What-If Analysis (Impact of Discount Adjustment on Profit)
A3: Base Total Sales: | B3: =SUM(Dataset!E2:E201)
A4: Base Total Profit: | B4: =SUM(Dataset!I2:I201)
A6: Discount Scenario Table
A7: Discount Shift | B7: Estimated Total Profit ($) | C7: Profit Change ($)
A8: -10% Reduction in Discount | B8: =B4 + (SUM(Dataset!E2:E201)*0.10*0.35) | C8: =B7-B4
A9: -5% Reduction in Discount | B9: =B4 + (SUM(Dataset!E2:E201)*0.05*0.35) | C9: =B8-B4
A10: Current Discount Level (Baseline) | B10: =B4 | C10: =B9-B4
A11: +5% Increase in Discount | B11: =B4 - (SUM(Dataset!E2:E201)*0.05*0.35) | C11: =B10-B4
A12: +10% Increase in Discount | B12: =B4 - (SUM(Dataset!E2:E201)*0.10*0.35) | C12: =B11-B4

Sheet Stats & Regression
A1: Task 3 & 4: Data Analysis (Descriptive Statistics & Linear Regression)
A3: Descriptive Statistics Summary
A4: Metric | B4: Sales ($) | C4: Profit ($) | D4: Quantity | E4: Discount (%)
A5: Mean | B5: =AVERAGE(Dataset!E2:E201) | C5: =AVERAGE(Dataset!I2:I201) | D5: =AVERAGE(Dataset!F2:F201) | E5: =AVERAGE(Dataset!G2:G201)
A6: Standard Deviation | B6: =STDEV.S(Dataset!E2:E201) | C6: =STDEV.S(Dataset!I2:I201) | D6: =STDEV.S(Dataset!F2:F201) | E6: =STDEV.S(Dataset!G2:G201)
A7: Minimum | B7: =MIN(Dataset!E2:E201) | C7: =MIN(Dataset!I2:I201) | D7: =MIN(Dataset!F2:F201) | E7: =MIN(Dataset!G2:G201)
A8: Median (Q2) | B8: =MEDIAN(Dataset!E2:E201) | C8: =MEDIAN(Dataset!I2:I201) | D8: =MEDIAN(Dataset!F2:F201) | E8: =MEDIAN(Dataset!G2:G201)
A9: Maximum | B9: =MAX(Dataset!E2:E201) | C9: =MAX(Dataset!I2:I201) | D9: =MAX(Dataset!F2:F201) | E9: =MAX(Dataset!G2:G201)
A10: Count | B10: =COUNT(Dataset!E2:E201) | C10: =COUNT(Dataset!I2:I201) | D10: =COUNT(Dataset!F2:F201) | E10: =COUNT(Dataset!G2:G201)
A12: Linear Regression Output (Profit vs Sales)
A13: Regression Parameter | B13: Value | C13: Interpretation
A14: R-Squared (R²) | B14: 0.598 | C14: 59.8% of Profit variance is explained by Sales
A15: Slope (Beta Coefficient) | B15: 0.3509 | C15: For every $1 increase in Sales, Profit increases by $0.35
A16: Intercept | B16: -1.0316 | C16: Base baseline constant coefficient
A17: F-Statistic | B17: 294.7 | C17: Model is highly statistically significant (p < 0.001)

Sheet Monthly Growth
A1: Task 5: Monthly Sales Growth & Custom Arrow Formatting
A3: Year-Month | B3: Total Sales ($) | C3: MoM Growth (%) | D3: Trend Arrow
A4: 2024-04 | B4: 19029.96 | C4: - | D4: -
A5: 2024-05 | B5: 18507.34 | C5: =(B5-B4)/B4 | D5: =IF(C5>0, "↑", IF(C5<0, "↓", "-"))
A6: 2024-06 | B6: 20187.51 | C6: =(B6-B5)/B5 | D6: =IF(C6>0, "↑", IF(C6<0, "↓", "-"))
A7: 2024-07 | B7: 11609.04 | C7: =(B7-B6)/B6 | D7: =IF(C7>0, "↑", IF(C7<0, "↓", "-"))
A8: 2024-08 | B8: 10091.7 | C8: =(B8-B7)/B7 | D8: =IF(C8>0, "↑", IF(C8<0, "↓", "-"))
A9: 2024-09 | B9: 20533.5 | C9: =(B9-B8)/B8 | D9: =IF(C9>0, "↑", IF(C9<0, "↓", "-"))
A10: 2024-10 | B10: 14215.24 | C10: =(B10-B9)/B9 | D10: =IF(C10>0, "↑", IF(C10<0, "↓", "-"))
A11: 2024-11 | B11: 20135.03 | C11: =(B11-B10)/B10 | D11: =IF(C11>0, "↑", IF(C11<0, "↓", "-"))
A12: 2024-12 | B12: 11120.04 | C12: =(B12-B11)/B11 | D12: =IF(C12>0, "↑", IF(C12<0, "↓", "-"))
A13: 2025-01 | B13: 14914.65 | C13: =(B13-B12)/B12 | D13: =IF(C13>0, "↑", IF(C13<0, "↓", "-"))
A14: 2025-02 | B14: 14006.36 | C14: =(B14-B13)/B13 | D14: =IF(C14>0, "↑", IF(C14<0, "↓", "-"))
A15: 2025-03 | B15: 17655.22 | C15: =(B15-B14)/B14 | D15: =IF(C15>0, "↑", IF(C15<0, "↓", "-"))
A16: 2025-04 | B16: 3212.17 | C16: =(B16-B15)/B15 | D16: =IF(C16>0, "↑", IF(C16<0, "↓", "-"))

Sheet High Value Customers
A1: Task 7: High-Value Customer Identification (INDEX & MATCH)
A3: Customer ID | B3: Customer Name | C3: Region | D3: Total Purchase ($) | E3: Total Profit ($) | F3: Total Quantity
A4: CUST030 | B4: Mary Davis | C4: East | D4: 2401.45 | E4: 1025.15 | F4: 23
A5: CUST008 | B5: James Wilson | C5: East | D5: 2095.36 | E5: 801.17 | F5: 33
A6: CUST026 | B6: Mary Davis | C6: East | D6: 2008.18 | E6: 594.97 | F6: 23
A7: CUST015 | B7: James Wilson | C7: West | D7: 1923.66 | E7: 769.46 | F7: 9
A8: CUST028 | B8: James Wilson | C8: Central | D8: 1771.03 | E8: 671.1 | F8: 15
A9: CUST002 | B9: Lisa Davis | C9: West | D9: 1770.15 | E9: 674.48 | F9: 25
A10: CUST015 | B10: James Wilson | C10: North | D10: 1681.21 | E10: 336.24 | F10: 5
A11: CUST005 | B11: Robert Anderson | C11: South | D11: 1679.97 | E11: 419.03 | F11: 14
A12: CUST024 | B12: Linda Taylor | C12: North | D12: 1622.62 | E12: 649.05 | F12: 12
A13: CUST002 | B13: Mary Jackson | C13: Central | D13: 1618.22 | E13: 582.56 | F13: 12
A14: CUST004 | B14: Mary Davis | C14: North | D14: 1589.42 | E14: 675.5 | F14: 6
A15: CUST014 | B15: Emma Davis | C15: West | D15: 1572.82 | E15: 672.38 | F15: 6
... A195: CUST028 | B195: Lisa Davis | C195: North | D195: 309.42 | E195: 111.39 | F195: 1

Sheet Pivot Table
A1: Task 8: Pivot Table (Sales by Region & Product Category)
A3: Region | B3: Books | C3: Clothing | D3: Electronics | E3: Furniture | F3: Office Supplies | G3: Grand Total
A4: Central | B4: 11297.15 | C4: 12200.26 | D4: 6621.24 | E4: 4876.96 | F4: 8472.72 | G4: =SUM(B4:F4)
A5: East | B5: 11389.09 | C5: 2401.45 | D5: 2869.54 | E5: 7592.34 | F5: 8189.22 | G5: =SUM(B5:F5)
A6: North | B6: 8037.01 | C6: 8422.82 | D6: 8191.71 | E6: 6978.08 | F6: 3345.8 | G6: =SUM(B6:F6)
A7: South | B7: 9588.04 | C7: 8393.63 | D7: 11989.07 | E7: 7982.73 | F7: 2295.32 | G7: =SUM(B7:F7)
A8: West | B8: 6691.17 | C8: 10509.43 | D8: 11372.44 | E8: 9182.78 | F8: 6327.76 | G8: =SUM(B8:F8)
A9: Grand Total | B9: =SUM(B4:B8) | C9: =SUM(C4:C8) | D9: =SUM(D4:D8) | E9: =SUM(E4:E8) | F9: =SUM(F4:F8) | G9: =SUM(G4:G8)
